<?xml version="1.0" ?><treatment xmlns="http://www.github.com/inbio" xmlns:xsi="http://www.w3.org/2001/XMLSchema-instance" xsi:schemaLocation="http://raw.githubusercontent.com/biosemantics/schemas/0.0.1/semanticMarkupOutput.xsd"><meta source="Nelson Zamora (Autor), Quírico Jiménez (Autor), Luis J. Poveda (Autor), Claudia Aragón (Ilustradora), Diana Ávila (editor), Rodrigo Gámez (prefacio) . Árboles de Costa Rica vol. IV. Primera edición (26 de Augosto, 2011)"><processor><processed_by operator="Maria Mora" date="Tue Jan 19 09:52:30 CST 2016"><resource type="Ontology Terms Organizer (OTO) Glossary"></resource><resource type="Plant Ontology"></resource><resource type="Language analysis tool: FreeLing" version="3.1"></resource></processed_by></processor></meta><taxon_identification taxon_name="Licaria pergamentacea W. C. Burger" rank="species"></taxon_identification><description taxon_description=" Árbol pequeño a grande, 10-30 m de altura; ramitas sólidas, con una pubescencia parda o amarillenta; estípulas ausentes. Hojas simples, alternas, 13-32 × 2,5-10 cm, elípticas u oblongo-elípticas, ápice acuminado, base aguda a obtusa, glabras y lisas, venas secundarias 8-14 pares por lado, margen entero; pecíolos 0,8-1,4 cm de largo. Inflorescencias en panículas, 8-14 cm de largo. Flores amarillas (bisexuales), 2 mm de largo. Frutos bayas, hasta 3 cm de largo, redondeadas; cúpula 1,5-1,8 × 1,6-2 cm, con el borde con un doble pliegue." description_type="morphology"><statement id="T109L1" text=" árbol pequeño a grande , 10-30 m de altura ;"><biological_entity id="T109L1S1-183031" name="árbol" type="structure"><character  name="size" value="pequeño" other_constraint="a" constraint_preposition="a grande"></character ><character  name="size_or_quantity" value="10-30" char_type="range_value" from="10" from_unit="m" to="30" to_unit="m" constraint_preposition="de altura ;"></character ></biological_entity></statement><statement id="T109L2" text=" ramitas sólidas , con una pubescencia parda o amarillenta ;"><biological_entity id="T109L2S1-183032" name="ramitas" constraint_preposition="con una pubescencia parda o amarillenta ;" type="structure"><character  name="architecture" value="sólidas"></character ></biological_entity><biological_entity id="T109L2S2-183033" name="pubescencia" type="structure"></biological_entity></statement><statement id="T109L3" text=" estípulas ausentes ."><biological_entity id="T109L3S1-183034" name="estípulas" type="structure"><character  name="quantity" value="ausentes"></character ></biological_entity></statement><statement id="T109L4" text=" hojas simples , alternas , 13-32 × 2,5-10 cm , elípticas u oblongo-elípticas , ápice acuminado , base aguda a obtusa , glabras y lisas , venas secundarias 8-14 pares por lado , margen entero ;"><biological_entity id="T109L4S1-183035" name="hojas" type="structure"><character  name="architecture" value="simples"></character ><character  name="arrangement" value="alternas"></character ><character  name="length" value="13-32" char_type="range_value" from="13" from_unit="cm" to="32" to_unit="cm"></character ><character  name="width" value="2,5-10" char_type="range_value" from="2,5" from_unit="cm" to="10" to_unit="cm"></character ><character  name="shape" value="elípticas" notes="Caracter repetido" constraint_conjunction="u"></character ><character  name="arrangement" value="elípticas" notes="Caracter repetido" constraint_conjunction="u"></character ><character  name="shape" value="oblongo-elípticas"></character ><character  name="pubescence" value="glabras" constraint_conjunction="y"></character ><character  name="architecture" value="lisas" notes="Caracter repetido"></character ><character  name="pubescence" value="lisas" notes="Caracter repetido"></character ><character  name="relief" value="lisas" notes="Caracter repetido"></character ></biological_entity><biological_entity id="T109L4S5-183036" name="ápice" type="structure"><character  name="shape" value="acuminado"></character ></biological_entity><biological_entity id="T109L4S6-183037" name="base" type="structure"><character  name="shape" value="aguda" other_constraint="a" constraint_preposition="a obtusa"></character ></biological_entity><biological_entity id="T109L4S8-183038" name="venas" type="structure"><character  name="position" value="secundarias" notes="Caracter repetido"></character ><character  name="structure_subtype" value="secundarias" notes="Caracter repetido"></character ><character  name="size_or_quantity" value="8-14" char_type="count" from="8" from_unit="pares" to="14" to_unit="pares" constraint_preposition="por lado"></character ></biological_entity><biological_entity id="T109L4S8-183039" name="lado" type="structure"></biological_entity><biological_entity id="T109L4S9-183040" name="margen" type="structure"><character  name="architecture" value="entero" notes="Caracter repetido"></character ><character  name="shape" value="entero" notes="Caracter repetido"></character ></biological_entity></statement><statement id="T109L5" text=" pecíolos 0,8-1,4 cm de largo ."><biological_entity id="T109L5S1-183041" name="pecíolos" type="structure"><character  name="size_or_quantity" value="0,8-1,4" char_type="range_value" from="0,8" from_unit="cm" to="1,4" to_unit="cm" constraint_preposition="de largo ."></character ></biological_entity></statement><statement id="T109L6" text=" inflorescencias en panículas , 8-14 cm de largo ."><biological_entity id="T109L6S1-183042" name="inflorescencias" constraint_preposition="en panículas" type="structure"></biological_entity><biological_entity id="T109L6S1-183043" name="panículas" type="structure"><character  name="size_or_quantity" value="8-14" char_type="range_value" from="8" from_unit="cm" to="14" to_unit="cm" constraint_preposition="de largo ."></character ></biological_entity></statement><statement id="T109L7" text=" flores amarillas ( bisexuales ) , 2 mm de largo ."><biological_entity id="T109L7S1-183044" name="flores" type="structure"><character  name="coloration" value="amarillas"></character ><character  name="reproduction" value="bisexuales"></character ><character  name="size_or_quantity" value="2" char_type="range_value" unit="mm" constraint_preposition="de largo ."></character ></biological_entity></statement><statement id="T109L8" text=" frutos bayas , hasta 3 cm de largo , redondeadas ;"><biological_entity id="T109L8S1-183045" name="frutos" constraint="bayas -" constraint_preposition="hasta 3 cm de largo" type="structure"><character  name="shape" value="redondeadas"></character ></biological_entity></statement><statement id="T109L9" text=" cúpula 1,5-1,8 × 1,6-2 cm , con el borde con un doble pliegue ."><biological_entity id="T109L9S1-183046" name="cúpula" constraint_preposition="con el borde con un doble pliegue ." type="structure"><character  name="length" value="1,5-1,8" char_type="range_value" from="1,5" from_unit="cm" to="1,8" to_unit="cm"></character ><character  name="width" value="1,6-2" char_type="range_value" from="1,6" from_unit="cm" to="2" to_unit="cm"></character ></biological_entity><biological_entity id="T109L9S2-183047" name="borde" type="structure"></biological_entity><biological_entity id="T109L9S2-183048" name="pliegue" type="structure"></biological_entity></statement></description></treatment>