<?xml version="1.0" ?><treatment xmlns="http://www.github.com/inbio" xmlns:xsi="http://www.w3.org/2001/XMLSchema-instance" xsi:schemaLocation="http://raw.githubusercontent.com/biosemantics/schemas/0.0.1/semanticMarkupOutput.xsd"><meta source="B. E. Hammel (Author, Editor), M. H. Grayum (Author, Editor), C. Herrera (Author, Editor), N. Zamora (Author, Editor). Manual de Plantas de Costa Rica, Volumen VI, Dicotiledoneas (Haloragaceae-Phytolaccaceae). Missouri Botanical Garden Press (October 26, 2007)"><processor><processed_by operator="Maria Mora" date="Wed Jan 20 20:28:19 CST 2016"><resource type="Ontology Terms Organizer (OTO) Glossary"></resource><resource type="Plant Ontology"></resource><resource type="Language analysis tool: FreeLing" version="3.1"></resource></processed_by></processor></meta><taxon_identification taxon_name="Beilschmiedia alloiophylla" rank="species"></taxon_identification><description taxon_description="Árbol, 8-35 metros, las ramitas jóvenes y yemas vegetativas densamente café-pubescentes con tricomas ± erectos y torcidos. Hojas agrupadas (raramente subalternas); pecíolo 0.7-3.5(- 4.5) cm; lámina 8-30 x 5-18 cm, oblonga a oblanceolada, obovada u oblongo-oblanceolada, cuneada u obtusa en la base, aguda a acuminada en el ápice, pubescente en el envés con tricomas erectos a glabrescente. Inflorescencias 8-30 centímetros. Flores con los tépalos aproximadamente. 1.5-2.1 milímetros. Frutos 2-4.5 centímetros." description_type="morphology"><statement id="T491L1" text=" árbol , 8-35 metros , las ramitas jóvenes y yemas vegetativas densamente café-pubescentes con tricomas ± erectos y torcidos ."><biological_entity id="T491L1S1-190970" name="árbol" type="structure"><character  name="size_or_quantity" value="8-35" char_type="count" from="8" from_unit="metros" to="35" to_unit="metros"></character ></biological_entity><biological_entity id="T491L1S3-190971" name="ramitas" constraint_conjunction="y" type="structure"><character  name="life_cycle" value="jóvenes"></character ></biological_entity><biological_entity id="T491L1S3-190972" name="yemas" type="structure"><character  name="reproduction" value="vegetativas"></character ><character  name="coloration" value="café-pubescentes" constraint="densamente -" constraint_preposition="con tricomas ± erectos y torcidos ."></character ></biological_entity><biological_entity id="T491L1S3-190973" name="tricomas" type="structure"></biological_entity></statement><statement id="T491L2" text=" hojas agrupadas ( raramente subalternas ) ;"><biological_entity id="T491L2S1-190974" name="hojas" type="structure"><character  name="arrangement" value="agrupadas"></character ><character  name="arrangement" value="subalternas" constraint="raramente"></character ></biological_entity></statement><statement id="T491L3" text=" pecíolo 0.7-3.5 ( -4.5 ) cm ;"><biological_entity id="T491L3S1-190975" name="pecíolo" type="structure"><character  name="size_or_quantity" value="0.7-3.5" char_type="range_value" from="0.7" from_unit="cm" to="3.5" to_unit="cm"></character ><character  name="atypical_range" value="-4.5" char_type="size_or_quantity" from="3.5" from_unit="cm" to="-4.5" to_unit="cm"></character ></biological_entity></statement><statement id="T491L4" text=" lámina 8-30 x 5-18 cm , oblonga a oblanceolada , obovada u oblongo-oblanceolada , cuneada u obtusa en la base , aguda a acuminada en el ápice , pubescente en el envés con tricomas erectos a glabrescente ."><biological_entity id="T491L4S1-190976" name="lámina" type="structure"><character  name="length" value="8-30" char_type="range_value" from="8" from_unit="cm" to="30" to_unit="cm"></character ><character  name="width" value="5-18" char_type="range_value" from="5" from_unit="cm" to="18" to_unit="cm"></character ><character  name="shape" value="oblonga" other_constraint="a" constraint_preposition="a oblanceolada"></character ><character  name="shape" value="obovada" constraint_conjunction="u"></character ><character  name="shape" value="oblongo-oblanceolada"></character ><character  name="shape" value="cuneada" constraint_conjunction="u"></character ><character  name="shape" value="obtusa" constraint_preposition="en la base"></character ></biological_entity><biological_entity id="T491L4S4-190977" name="base" type="structure"><character  name="shape" value="aguda" other_constraint="a" constraint_preposition="a acuminada en el ápice"></character ></biological_entity><biological_entity id="T491L4S5-190978" name="ápice" type="structure"><character  name="pubescence" value="pubescente" constraint_preposition="en el envés con tricomas erectos a glabrescente ."></character ></biological_entity><biological_entity id="T491L4S6-190979" name="envés" type="structure"></biological_entity><biological_entity id="T491L4S6-190980" name="tricomas" type="structure"></biological_entity></statement><statement id="T491L5" text=" inflorescencias 8-30 centímetros ."><biological_entity id="T491L5S1-190981" name="inflorescencias" type="structure"><character  name="size_or_quantity" value="8-30" char_type="count" from="8" from_unit="centímetros" to="30" to_unit="centímetros"></character ></biological_entity></statement><statement id="T491L6" text=" flores con los tépalos aproximadamente . 1.5-2.1 milímetros ."><biological_entity id="T491L6S1-190982" name="flores" constraint_preposition="con los tépalos aproximadamente . 1.5-2.1 milímetros ." type="structure"></biological_entity><biological_entity id="T491L6S1-190983" name="tépalos" type="structure"></biological_entity></statement><statement id="T491L7" text=" frutos 2-4.5 centímetros ."><biological_entity id="T491L7S1-190984" name="frutos" type="structure"><character  name="size_or_quantity" value="2-4.5" char_type="count" from="2" from_unit="centímetros" to="4.5" to_unit="centímetros"></character ></biological_entity></statement></description></treatment>